Metadata-Version: 1.1
Name: qs-qrcode
Version: 1.1
Summary: generate qrcode
Home-page: http://github.com/tomhaoye/qrcode
Author: Q
Author-email: tomhaoye@gmail.com
License: MIT
Platform: UNKNOWN
Classifier: Intended Audience :: Developers
Classifier: Operating System :: OS Independent
Classifier: License :: OSI Approved :: MIT License
Classifier: Topic :: Multimedia :: Graphics
Classifier: Topic :: Software Development :: Libraries :: Python Modules
Classifier: Programming Language :: Python
Classifier: Programming Language :: Python :: 3.5
Classifier: Programming Language :: Python :: 3.6
